[
  {"id":1,"word":"pen","transcription":"pen","translation":"ручка","image":""},
  {"id":2,"word":"pencil","transcription":"ˈpens(ə)l","translation":"карандаш",""},
  {"id":3,"word":"rubber","transcription":"ˈrʌbə","translation":"ластик","image":""},
  {"id":4,"word":"ruler","transcription":"ˈruːlə","translation":"линейка","image":""},
  {"id":5,"word":"book","transcription":"bʊk","translation":"книга","image":""},
  {"id":6,"word":"orange","transcription":"ˈɒrɪndʒ","translation":"апельсин","image":""},
  {"id":7,"word":"train","transcription":"treɪn","translation":"поезд","image":""},
  {"id":8,"word":"plane","transcription":"pleɪn","translation":"самолёт","image":""},
  {"id":9,"word":"ball","transcription":"bɔːl","translation":"мяч","image":""},
  {"id":10,"word":"umbrella","transcription":"ʌmˈbrelə","translation":"зонт","image":""}
]
